googletrans_wheel/__init__.py
googletrans_wheel/client.py
googletrans_wheel/constants.py
googletrans_wheel/gtoken.py
googletrans_wheel/models.py
googletrans_wheel/urls.py
googletrans_wheel/utils.py
googletrans_wheel-3.0.0.data/scripts/translate
googletrans_wheel-3.0.0.dist-info/METADATA
googletrans_wheel-3.0.0.dist-info/WHEEL
googletrans_wheel-3.0.0.dist-info/top_level.txt
googletrans_wheel-3.0.0.dist-info/RECORD
