Metadata-Version: 2.1
Name: googletrans_wheel
Version: 3.0.0
Summary: Free Google Translate API for Python. Translates totally free of charge.
Home-page: https://github.com/ssut/py-googletrans
Author: SuHun Han
Author-email: ssut@ssut.me
License: MIT
Keywords: google translate translator
Classifier: Development Status :: 5 - Production/Stable
Classifier: Intended Audience :: Education
Classifier: Intended Audience :: End Users/Desktop
Classifier: License :: Freeware
Classifier: Operating System :: POSIX
Classifier: Operating System :: Microsoft :: Windows
Classifier: Operating System :: MacOS :: MacOS X
Classifier: Topic :: Education
Classifier: Programming Language :: Python
Classifier: Programming Language :: Python :: 3.6
Classifier: Programming Language :: Python :: 3.7
Classifier: Programming Language :: Python :: 3.8
Requires-Dist: httpx ==0.13.3
